<?xml version="1.0" encoding="UTF-8"?>
<!DOCTYPE suite SYSTEM "https://testng.org/testng-1.0.dtd">
<suite name="Suite">
<groups>
<run>
<include name = "smokeTest">
</include>
</run>
</groups>
  <test thread-count="5" name="Test">
    <classes>
      <class name="com.crm.sdet.Cmpaign.CreateCampaignTest"/>
      <class name="com.crm.sdet.Cmpaign.CreateCampaignANDproductTest"/>
      <class name="com.crm.sdet.Product.CreateProductANDdeleteProductTest"/>
      <class name="com.crm.sdet.Organization.CreateOrgnizationTest"/>
      <class name="com.crm.sdet.Product.CreateProductTest"/>
    </classes>
  </test> <!-- Test -->
</suite> <!-- Suite -->
